filecabinet/__init__.py
filecabinet/cabinet.py
filecabinet/configuration.py
filecabinet/main.py
filecabinet/manager.py
filecabinet/meta.py
filecabinet/shell.py
filecabinet/utils.py
filecabinet/version.py
filecabinet-2.1.0.dist-info/LICENSE
filecabinet-2.1.0.dist-info/METADATA
filecabinet-2.1.0.dist-info/WHEEL
filecabinet-2.1.0.dist-info/entry_points.txt
filecabinet-2.1.0.dist-info/top_level.txt
filecabinet-2.1.0.dist-info/RECORD
