Metadata-Version: 2.1
Name: filecabinet
Version: 2.1.0
Summary: A local, offline document archive
Home-page: https://vonshednob.cc/filecabinet
Author: R
Author-email: dev+filecabinet-this-is-spam@vonshednob.cc
License: Copyright 2023 Robert Labudda All Rights Reserved.
Classifier: Development Status :: 3 - Alpha
Classifier: License :: OSI Approved :: BSD License
Classifier: Programming Language :: Python :: 3
Requires-Python: >=3.7
License-File: LICENSE
Requires-Dist: pyyaml
Requires-Dist: pypdf
Requires-Dist: Pillow
Requires-Dist: metaindex (>=2.3.0)
